choquet_classifier_glenscalai/__init__.py
choquet_classifier_glenscalai/choquet_classifier.py
choquet_classifier_glenscalai/mediator/__init__.py
choquet_classifier_glenscalai/mediator/fitter.py
choquet_classifier_glenscalai/mediator/mediator.py
choquet_classifier_glenscalai/mediator/predictor.py
choquet_classifier_glenscalai/mediator/components/__init__.py
choquet_classifier_glenscalai/mediator/components/choquet_integral.py
choquet_classifier_glenscalai/mediator/components/choquistic_regression.py
choquet_classifier_glenscalai/mediator/components/feature_transformation.py
choquet_classifier_glenscalai/mediator/components/helper.py
choquet_classifier_glenscalai/mediator/components/parameter_estimation.py
choquet_classifier_glenscalai-0.0.1.dist-info/METADATA
choquet_classifier_glenscalai-0.0.1.dist-info/WHEEL
choquet_classifier_glenscalai-0.0.1.dist-info/licenses/LICENSE
choquet_classifier_glenscalai-0.0.1.dist-info/RECORD
