Metadata-Version: 2.1
Name: choquet_classifier_glenscalai
Version: 0.0.1
Summary: An implementation of the monotone nonlinear Choquet classifier for binary classification
Project-URL: Homepage, https://github.com/glenbreaks/choquet-classifier
Project-URL: Bug Tracker, https://github.com/glenbreaks/choquet-classifier/issues
Author-email: Daniel Ebensberger <glenbreaks106@gmail.com>
License-File: LICENSE
Classifier: Development Status :: 3 - Alpha
Classifier: License :: OSI Approved :: MIT License
Classifier: Operating System :: OS Independent
Classifier: Programming Language :: Python :: 3
Requires-Python: >=3.9
Requires-Dist: numpy>=1.23
Requires-Dist: scikit-learn>=1.1.1
Requires-Dist: scipy>=1.9.1
